rollme
