Metadata-Version: 1.0
Name: rollme
Version: 0.0.6
Summary: Python script to roll the dice
Home-page: https://github.com/psyclone241/rollme
Author: Roy Keyes
Author-email: keyes.roy@gmail.com
License: UNKNOWN
Platform: UNKNOWN
